prospector/__init__.py
prospector/__main__.py
prospector/autodetect.py
prospector/blender.py
prospector/blender_combinations.yaml
prospector/compat.py
prospector/config/__init__.py
prospector/config/configuration.py
prospector/config/datatype.py
prospector/encoding.py
prospector/exceptions.py
prospector/finder.py
prospector/formatters/__init__.py
prospector/formatters/base.py
prospector/formatters/base_summary.py
prospector/formatters/emacs.py
prospector/formatters/gitlab.py
prospector/formatters/grouped.py
prospector/formatters/json.py
prospector/formatters/pylint.py
prospector/formatters/pylint_parseable.py
prospector/formatters/text.py
prospector/formatters/vscode.py
prospector/formatters/xunit.py
prospector/formatters/yaml.py
prospector/identify.py
prospector/message.py
prospector/pathutils.py
prospector/postfilter.py
prospector/profiles/__init__.py
prospector/profiles/exceptions.py
prospector/profiles/profile.py
prospector/profiles/profiles/default.yaml
prospector/profiles/profiles/doc_warnings.yaml
prospector/profiles/profiles/flake8.yaml
prospector/profiles/profiles/full_pep8.yaml
prospector/profiles/profiles/member_warnings.yaml
prospector/profiles/profiles/no_doc_warnings.yaml
prospector/profiles/profiles/no_member_warnings.yaml
prospector/profiles/profiles/no_pep8.yaml
prospector/profiles/profiles/no_test_warnings.yaml
prospector/profiles/profiles/strictness_high.yaml
prospector/profiles/profiles/strictness_low.yaml
prospector/profiles/profiles/strictness_medium.yaml
prospector/profiles/profiles/strictness_none.yaml
prospector/profiles/profiles/strictness_veryhigh.yaml
prospector/profiles/profiles/strictness_verylow.yaml
prospector/profiles/profiles/test_warnings.yaml
prospector/run.py
prospector/suppression.py
prospector/tools/__init__.py
prospector/tools/bandit/__init__.py
prospector/tools/base.py
prospector/tools/dodgy/__init__.py
prospector/tools/exceptions.py
prospector/tools/mccabe/__init__.py
prospector/tools/mypy/__init__.py
prospector-1.17.3.dist-info/LICENSE
prospector-1.17.3.dist-info/METADATA
prospector-1.17.3.dist-info/WHEEL
prospector-1.17.3.dist-info/entry_points.txt
prospector-1.17.3.dist-info/RECORD
