Metadata-Version: 2.3
Name: prospector
Version: 1.17.3
Summary: Prospector is a tool to analyse Python code by aggregating the result of other tools.
License: GPLv2+
Keywords: prospector,pylint,static code analysis
Author: Carl Crowder
Author-email: git@carlcrowder.com
Maintainer: Carl Crowder
Maintainer-email: git@carlcrowder.com
Requires-Python: >=3.9
Classifier: Development Status :: 5 - Production/Stable
Classifier: Environment :: Console
Classifier: Intended Audience :: Developers
Classifier: License :: OSI Approved :: GNU General Public License v2 or later (GPLv2+)
Classifier: Operating System :: Unix
Classifier: Programming Language :: Python :: 3 :: Only
Classifier: Programming Language :: Python :: 3.9
Classifier: Programming Language :: Python :: 3.10
Classifier: Programming Language :: Python :: 3.11
Classifier: Programming Language :: Python :: 3.12
Classifier: Programming Language :: Python :: 3.13
Classifier: Topic :: Software Development :: Quality Assurance
Provides-Extra: with-bandit
Provides-Extra: with-everything
Provides-Extra: with-mypy
Provides-Extra: with-pyright
Provides-Extra: with-pyroma
Provides-Extra: with-ruff
Provides-Extra: with-vulture
Requires-Dist: PyYAML
Requires-Dist: bandit ; extra == "with-bandit"
Requires-Dist: bandit ; extra == "with-everything"
Requires-Dist: dodgy (>=0.2.1,<0.3.0)
Requires-Dist: mccabe (>=0.7.0,<0.8.0)
Requires-Dist: mypy ; extra == "with-everything"
Requires-Dist: mypy ; extra == "with-mypy"
Requires-Dist: packaging
Requires-Dist: pep8-naming (>=0.3.3,<=0.10.0)
Requires-Dist: pycodestyle (>=2.9.0)
Requires-Dist: pydocstyle (>=2.0.0)
Requires-Dist: pyflakes (>=2.2.0)
Requires-Dist: pylint (>=3.0)
Requires-Dist: pylint-celery (==0.3)
Requires-Dist: pylint-django (>=2.6.1)
Requires-Dist: pyright ; extra == "with-everything"
Requires-Dist: pyright ; extra == "with-pyright"
Requires-Dist: pyroma ; extra == "with-everything"
Requires-Dist: pyroma ; extra == "with-pyroma"
Requires-Dist: requirements-detector (>=1.3.2)
Requires-Dist: ruff ; extra == "with-everything"
Requires-Dist: ruff ; extra == "with-ruff"
Requires-Dist: setoptconf-tmp (>=0.3.1,<0.4.0)
Requires-Dist: toml (>=0.10.2,<0.11.0)
Requires-Dist: vulture ; extra == "with-everything"
Requires-Dist: vulture ; extra == "with-vulture"
Project-URL: Bug Tracker, https://github.com/prospector-dev/prospector/issues
Project-URL: Homepage, http://prospector.readthedocs.io
Project-URL: Repository, https://github.com/prospector-dev/prospector
